setup.py
django_saas_user.egg-info/PKG-INFO
django_saas_user.egg-info/SOURCES.txt
django_saas_user.egg-info/dependency_links.txt
django_saas_user.egg-info/not-zip-safe
django_saas_user.egg-info/top_level.txt
saas_users/__init__.py
saas_users/admin.py
saas_users/backends.py
saas_users/models.py
saas_users/settings.py
saas_users/signals.py
saas_users/utils.py