Metadata-Version: 1.1
Name: django-saas-user
Version: 0.2
Summary: Multi-client Authentication/Authorization for Django
Home-page: http://github.com/commoncode/gambit
Author: Curtis Maloney
Author-email: curtis@commoncode.com.au
License: UNKNOWN
Keywords: django
Platform: UNKNOWN
Classifier: Environment :: Web Environment
Classifier: Framework :: Django
Classifier: License :: OSI Approved :: BSD License
Classifier: Operating System :: OS Independent
Classifier: Programming Language :: Python
Requires: Django (>=1.6)
